lazy_import/VERSION
lazy_import/__init__.py
lazy_import/test_lazy.py
sloth_import-0.2.3.dist-info/DESCRIPTION.rst
sloth_import-0.2.3.dist-info/METADATA
sloth_import-0.2.3.dist-info/RECORD
sloth_import-0.2.3.dist-info/WHEEL
sloth_import-0.2.3.dist-info/metadata.json
sloth_import-0.2.3.dist-info/top_level.txt
